typedmongo-1.18.3.dist-info/METADATA
typedmongo-1.18.3.dist-info/WHEEL
typedmongo-1.18.3.dist-info/entry_points.txt
typedmongo-1.18.3.dist-info/licenses/LICENSE
typedmongo/__init__.py
typedmongo/asyncio/__init__.py
typedmongo/asyncio/client.py
typedmongo/asyncio/fields.py
typedmongo/asyncio/table.py
typedmongo/client.py
typedmongo/exceptions.py
typedmongo/expressions.py
typedmongo/fields.py
typedmongo/marshamallow.py
typedmongo/shortcuts.py
typedmongo/sync.py
typedmongo/table.py
typedmongo-1.18.3.dist-info/RECORD
