Metadata-Version: 2.1
Name: typedmongo
Version: 1.18.3
Summary: A production-ready modern Python MongoDB ODM
Author-Email: abersheeran <me@abersheeran.com>
License: Apache2.0
Requires-Python: >=3.10
Requires-Dist: pymongo>=4.13.2
Requires-Dist: marshmallow>=4.0.0
Requires-Dist: typing-extensions>=4.11.0
Provides-Extra: pydantic
Requires-Dist: pydantic>=2; extra == "pydantic"
